{
  "section_id": "section2",
  "title": "セクション2_問題",
  "questions": [
    {
      "id": "s2q1",
      "question_number": 1,
      "difficulty": "H",
      "text": "「訪問看護（リハビリ）計画書」について、新入職員の理解として最も適切なものはどれですか。",
      "options": [
        {
          "letter": "A",
          "text": "主治医の指示やケアプランに基づき、ステーションとしてどのような看護・リハビリを、何の目標に向けて提供するかを明確にし、利用者・家族に説明・同意を得るための書類である。",
          "is_correct": true
        },
        {
          "letter": "B",
          "text": "厚生労働省や役所に提出するためだけの書類であり、現場のケア内容には影響しない。",
          "is_correct": false
        },
        {
          "letter": "C",
          "text": "看護師やリハビリ職が、毎月の売上（算定）を確保するために、架張の目標を並べるための書類である。",
          "is_correct": false
        },
        {
          "letter": "D",
          "text": "一度作成したら、利用者が退院するか亡くなるまで、内容を一切変更してはならない書類である。",
          "is_correct": false
        }
      ],
      "correct_answer": "A",
      "explanation": {
        "summary": "計画書はサービス提供の指針であり、利用者や家族に交付して同意を得ることが制度上の必須要件（算定要件）となっています。",
        "detailed": "日本訪問看護財団「日本の訪問看護のしくみ」"
      }
    },
    {
      "id": "s2q2",
      "question_number": 2,
      "difficulty": "H",
      "text": "前任者が作成した計画書を引き継いだ際、新入職員が実務的ミス（計画に沿わないケア）を防ぐために、計画書から必ず読み取るべき最重要項目はどれですか。",
      "options": [
        {
          "letter": "A",
          "text": "文字数が何文字以上で書かれているかという形式的な部分だけ。",
          "is_correct": false
        },
        {
          "letter": "B",
          "text": "解決すべき課題と看護・リハビリの目標、およびそれに対する具体的な支援内容を確認し、今行おうとしているケアがその目標に直結しているかを確認する。",
          "is_correct": true
        },
        {
          "letter": "C",
          "text": "計画書に記載されている事業所の固定電話番号や住所が合っているか。",
          "is_correct": false
        },
        {
          "letter": "D",
          "text": "前任者の個人的な感想や、利用者の愚痴がどれくらい書かれているか。",
          "is_correct": false
        }
      ],
      "correct_answer": "B",
      "explanation": {
        "summary": "計画書に書かれた目標や課題を無視して、その日の思いつきでケアやリハビリを行うことは、計画書違反（減算や実地指導での指摘対象）となります。",
        "detailed": "日本訪問看護財団「日本の訪問看護のしくみ」"
      }
    },
    {
      "id": "s2q3",
      "question_number": 3,
      "difficulty": "H",
      "text": "毎月主治医やケアマネジャーに提出する「訪問看護報告書」の実務上の役割について、正しい説明はどれですか。",
      "options": [
        {
          "letter": "A",
          "text": "ステーションの内部だけで保管し、外部の人間には絶対に見せてはならない秘密の記録。",
          "is_correct": false
        },
        {
          "letter": "B",
          "text": "利用者の家族に、毎日の愚痴や不満を報告して反省を促すための書類。",
          "is_correct": false
        },
        {
          "letter": "C",
          "text": "ケアマネジャーに「これだけ働いたのでお金をください」と請求するためだけの請求明細書。",
          "is_correct": false
        },
        {
          "letter": "D",
          "text": "1ヶ月間に実施した看護・リハビリの具体的な内容や回数、利用者の状態の変化を医師に正確に伝え、次月の指示書の継続・変更の判断材料にしてもらうための書類。",
          "is_correct": true
        }
      ],
      "correct_answer": "D",
      "explanation": {
        "summary": "報告書は、主治医が次月の訪問看護指示書を発行するかどうかの重要な医学的判断材料になります。正確かつ客観的な記載が求められます。",
        "detailed": "日本訪問看護財団「日本の訪問看護のしくみ」"
      }
    },
    {
      "id": "s2q4",
      "question_number": 4,
      "difficulty": "H",
      "text": "報告書に利用者の様子を記載する際、実務的な不備（実地指導等での指摘）を避けるための最も適切な記述方法はどれですか。",
      "options": [
        {
          "letter": "A",
          "text": "いつも通り元気そうだった。特に変わったことはないと思われる。今後も継続する。と簡潔に3行程度で済ませる。",
          "is_correct": false
        },
        {
          "letter": "B",
          "text": "利用者が話していた世間話や政治の意見を、そのままノート2ページ分書き写す。",
          "is_correct": false
        },
        {
          "letter": "C",
          "text": "血圧等バイタルは安定。下肢の浮腫は前月より軽減し、自力での歩行距離が5mから10mに延長している。排便は2日に1回あり、性状は普通便。と具体的に書く。",
          "is_correct": true
        },
        {
          "letter": "D",
          "text": "リハビリの専門用語や英語の略称だけを並べ、医師やケアマネジャーが読んでも意味がわからないように書く。",
          "is_correct": false
        }
      ],
      "correct_answer": "C",
      "explanation": {
        "summary": "報告書は多職種や医師が読めて納得できる、客観的・具体的な数値や状態の変化が記載されている必要があります。「いつも通り」「良好」などの曖昧な表現は不適切とみなされます。",
        "detailed": "日本訪問看護財団「日本の訪問看護のしくみ」"
      }
    },
    {
      "id": "s2q5",
      "question_number": 5,
      "difficulty": "H",
      "text": "訪問時の記録（カルテ・実績記録）を作成する際、新入職員が陥りやすい「主観的な記録（実務上不適切）」はどれですか。",
      "options": [
        {
          "letter": "A",
          "text": "体温36.5℃、脈拍72回/分、整。顔色は普段と変わらず、食事は全量摂取されていた。",
          "is_correct": false
        },
        {
          "letter": "B",
          "text": "利用者はリハビリに対してやる気がなさそうに見えた。わがままを言っている。",
          "is_correct": true
        },
        {
          "letter": "C",
          "text": "リハビリの開始を促した際、利用者は「今日は体がだるいから動きたくない」と発言し、訓練を拒否された。",
          "is_correct": false
        },
        {
          "letter": "D",
          "text": "室温が28℃と高く、本人は汗をかいていたため、エアコンの作動を提案し実施した。",
          "is_correct": false
        }
      ],
      "correct_answer": "B",
      "explanation": {
        "summary": "記録は「事実（客観）」ベースで書くべきであり、「やる気がない」「わがまま」といった職員の主観や感情、偏見を交えた表現は実務上非常に不適切です。",
        "detailed": "日本看護協会「訪問看護」"
      }
    },
    {
      "id": "s2q6",
      "question_number": 6,
      "difficulty": "M",
      "text": "利用者の食事摂取量について記録する際、実務的な記録として最も優れているものはどれですか。",
      "options": [
        {
          "letter": "A",
          "text": "朝食：全粥茶碗1杯、味噌汁半分、卵焼き1切れ（全体の約8割）を自力で摂取。むせ込みなし。",
          "is_correct": true
        },
        {
          "letter": "B",
          "text": "朝食はそこそこ食べていた。食欲は普通にあるようだ。",
          "is_correct": false
        },
        {
          "letter": "C",
          "text": "ご飯をたくさん食べて元気いっぱいだった。",
          "is_correct": false
        },
        {
          "letter": "D",
          "text": "食事の量は日によって違うが、今日はまあまあだった。",
          "is_correct": false
        }
      ],
      "correct_answer": "A",
      "explanation": {
        "summary": "食事量や水分摂取量は、「そこそこ」「まあまあ」ではなく、具体的な量（何割、何ml、皿の数など）と、摂取時の状況（自力、全介助、むせの有無など）を記載するのが正しい実務です。",
        "detailed": "日本看護協会「訪問看護」"
      }
    },
    {
      "id": "s2q7",
      "question_number": 7,
      "difficulty": "H",
      "text": "利用者の状態が急変（呼吸苦の訴え、サチュレーション低下）し、主治医に緊急の電話報告を行うことになりました。新人が意識すべき報告の優先順位（伝える順番）として最も適切なものはどれですか。",
      "options": [
        {
          "letter": "A",
          "text": "1：今月の訪問回数の確認、2：現在の症状、3：主治医の機嫌伺い。",
          "is_correct": false
        },
        {
          "letter": "B",
          "text": "1：利用者の過去の病歴、2：利用者の家族の愚痴、3：現在の症状、4：ステーションの最近のニュース。",
          "is_correct": false
        },
        {
          "letter": "C",
          "text": "まずは世間話から始め、場が和んだところで徐々に利用者の体調の話に移行する。",
          "is_correct": false
        },
        {
          "letter": "D",
          "text": "1：自分の氏名・ステーション名、2：該当の利用者名、3：現在の最も深刻な症状とバイタル、4：発症からの経過、5：現在の対応と医師への要望（指示の仰ぎ）。",
          "is_correct": true
        }
      ],
      "correct_answer": "D",
      "explanation": {
        "summary": "医師への緊急報告では、結論（誰が、どうなったか、何を求めているか）を最優先で簡潔に伝える必要があります。情報の整理にはSBAR（状況・背景・アセスメント・提案）のフレームワークが有効です。",
        "detailed": "日本看護協会「訪問看護」"
      }
    },
    {
      "id": "s2q8",
      "question_number": 8,
      "difficulty": "H",
      "text": "主治医への報告の際、緊張して状況をうまく伝えられない新人が、事前に準備しておくべき実務的なメモとして、最も不適切な内容はどれですか。",
      "options": [
        {
          "letter": "A",
          "text": "現在のバイタルサイン、意識レベル、具体的な症状の発生時刻を記した最新のデータ。",
          "is_correct": false
        },
        {
          "letter": "B",
          "text": "主治医から過去に出ていた指示内容（「〜の時は連絡して」など）の確認メモ。",
          "is_correct": false
        },
        {
          "letter": "C",
          "text": "利用者の若かりし頃の思い出話や、趣味の遍歴を詳しくまとめたメモ。",
          "is_correct": true
        },
        {
          "letter": "D",
          "text": "自分が医師に何をしてほしいか（臨時往診、指示の変更、処置の許可など）の明確な要望。",
          "is_correct": false
        }
      ],
      "correct_answer": "C",
      "explanation": {
        "summary": "緊急報告時に不要なエピソードを盛り込むと、医師が状況を誤認したり、判断が遅れたりするリスクがあります。医学的・実務的な事実のみを整理します。※不適切なものを問う設問のため、不要な情報である選択肢Cが正解となります。",
        "detailed": "日本看護協会「訪問看護」"
      }
    },
    {
      "id": "s2q9",
      "question_number": 9,
      "difficulty": "H",
      "text": "毎月の終わりにケアマネジャーに提出する「サービス提供実績（サービス提供票の実績欄）」の処理について、新入職員が行うべき正しい実務はどれですか。",
      "options": [
        {
          "letter": "A",
          "text": "予定と実績の報告は1年に1回まとめて行えばよい。",
          "is_correct": false
        },
        {
          "letter": "B",
          "text": "予定通り訪問した日、キャンセルになった日、臨時で訪問した日を、ケアプランの日付と正確に照合し、相違がないか確認して確定させる。",
          "is_correct": true
        },
        {
          "letter": "C",
          "text": "ケアマネジャーに報告するのは面倒なので、予定通りにすべて訪問したことにして一括でハンコを押す。",
          "is_correct": false
        },
        {
          "letter": "D",
          "text": "キャンセルになった日も、事業所の売上のために「訪問した」と嘘の実績を記載する。",
          "is_correct": false
        }
      ],
      "correct_answer": "B",
      "explanation": {
        "summary": "ケアマネジャーはサービス提供実績に基づいて給付管理（単位数の計算）を行います。実績に1箇所でもズレがあると、保険請求がエラー（返戻）になり、事業所やケアマネジャーに多大な迷惑がかかります。",
        "detailed": "日本訪問看護財団「日本の訪問看護のしくみ」"
      }
    },
    {
      "id": "s2q10",
      "question_number": 10,
      "difficulty": "M",
      "text": "訪問看護計画書や報告書の作成・提出が期日（翌月の初頭など）より大幅に遅れてしまいました。この遅れがもたらす事業所や実務上の最大のリスクはどれですか。",
      "options": [
        {
          "letter": "A",
          "text": "適切な書類管理が行われていないとみなされ、自治体の実地指導（監査）において「未作成減算」や「指導」の対象となり、最悪の場合は過去に遡って報酬の返還を求められる。",
          "is_correct": true
        },
        {
          "letter": "B",
          "text": "書類が遅れても、ケア自体は提供しているので、法的なペナルティやリスクは一切存在しない。",
          "is_correct": false
        },
        {
          "letter": "C",
          "text": "ケアマネジャーが少し困るだけで、ステーション側の実務や請求には何も影響しない。",
          "is_correct": false
        },
        {
          "letter": "D",
          "text": "医師からの信頼が上がる。",
          "is_correct": false
        }
      ],
      "correct_answer": "A",
      "explanation": {
        "summary": "訪問看護・リハビリの報酬は、適切な書類が期日までに作成され、適切に交付・同意・提出されていることが算定の絶対条件です。書類の遅れや未作成は重大な制度違反です。",
        "detailed": "日本訪問看護財団「日本の訪問看護のしくみ」"
      }
    }
  ]
}
